{
  "DbinvoiceTaxData" : {
    "_id" : "wm-DbinvoiceTaxData-wm.LiveVariable-1498645802019",
    "name" : "DbinvoiceTaxData",
    "owner" : "Page",
    "category" : "wm.LiveVariable",
    "dataBinding" : [ ],
    "operation" : "read",
    "dataSet" : [ ],
    "type" : "Tax",
    "isList" : true,
    "saveInPhonegap" : false,
    "maxResults" : 20,
    "designMaxResults" : 10,
    "inFlightBehavior" : "executeLast",
    "startUpdate" : true,
    "autoUpdate" : true,
    "transformationRequired" : false,
    "liveSource" : "dbinvoice",
    "ignoreCase" : true,
    "matchMode" : "start",
    "propertiesMap" : {
      "columns" : [ {
        "fieldName" : "taxType",
        "type" : "integer",
        "fullyQualifiedType" : "integer",
        "columnName" : "taxType_id",
        "isPrimaryKey" : false,
        "notNull" : false,
        "length" : 0,
        "precision" : 10,
        "generator" : "assigned",
        "isRelated" : true,
        "defaultValue" : "",
        "relatedTableName" : "taxType",
        "relatedEntityName" : "TaxType",
        "relatedColumnName" : "taxTypeId",
        "relatedFieldName" : "taxType.id",
        "isList" : false,
        "targetTable" : "taxType",
        "scale" : 0,
        "columns" : [ {
          "fieldName" : "id",
          "type" : "integer",
          "fullyQualifiedType" : "integer",
          "columnName" : "ID",
          "isPrimaryKey" : true,
          "notNull" : true,
          "length" : 0,
          "precision" : 10,
          "generator" : "identity",
          "isRelated" : false,
          "defaultValue" : "",
          "scale" : 0
        }, {
          "fieldName" : "name",
          "type" : "string",
          "fullyQualifiedType" : "string",
          "columnName" : "name",
          "isPrimaryKey" : false,
          "notNull" : false,
          "length" : 255,
          "precision" : 0,
          "generator" : "assigned",
          "isRelated" : false,
          "defaultValue" : "",
          "scale" : 0
        } ]
      }, {
        "fieldName" : "fiscalSpace",
        "type" : "integer",
        "fullyQualifiedType" : "integer",
        "columnName" : "fiscalSpace_id",
        "isPrimaryKey" : false,
        "notNull" : false,
        "length" : 0,
        "precision" : 10,
        "generator" : "assigned",
        "isRelated" : true,
        "defaultValue" : "",
        "relatedTableName" : "fiscalSpace",
        "relatedEntityName" : "FiscalSpace",
        "relatedColumnName" : "fiscalSpaceId",
        "relatedFieldName" : "fiscalSpace.id",
        "isList" : false,
        "targetTable" : "fiscalSpace",
        "scale" : 0,
        "columns" : [ {
          "fieldName" : "id",
          "type" : "integer",
          "fullyQualifiedType" : "integer",
          "columnName" : "ID",
          "isPrimaryKey" : true,
          "notNull" : true,
          "length" : 0,
          "precision" : 10,
          "generator" : "identity",
          "isRelated" : false,
          "defaultValue" : "",
          "scale" : 0
        }, {
          "fieldName" : "name",
          "type" : "string",
          "fullyQualifiedType" : "string",
          "columnName" : "name",
          "isPrimaryKey" : false,
          "notNull" : false,
          "length" : 255,
          "precision" : 0,
          "generator" : "assigned",
          "isRelated" : false,
          "defaultValue" : "",
          "scale" : 0
        } ]
      }, {
        "fieldName" : "country",
        "type" : "integer",
        "fullyQualifiedType" : "integer",
        "columnName" : "country_id",
        "isPrimaryKey" : false,
        "notNull" : false,
        "length" : 0,
        "precision" : 10,
        "generator" : "assigned",
        "isRelated" : true,
        "defaultValue" : "",
        "relatedTableName" : "country",
        "relatedEntityName" : "Country",
        "relatedColumnName" : "countryId",
        "relatedFieldName" : "country.id",
        "isList" : false,
        "targetTable" : "country",
        "scale" : 0,
        "columns" : [ {
          "fieldName" : "timezone",
          "type" : "integer",
          "fullyQualifiedType" : "integer",
          "columnName" : "timezone_id",
          "isPrimaryKey" : false,
          "notNull" : false,
          "length" : 0,
          "precision" : 10,
          "generator" : "assigned",
          "isRelated" : true,
          "defaultValue" : "",
          "relatedColumnName" : "timezoneId",
          "targetTable" : "timezone",
          "scale" : 0
        }, {
          "fieldName" : "language",
          "type" : "integer",
          "fullyQualifiedType" : "integer",
          "columnName" : "language_id",
          "isPrimaryKey" : false,
          "notNull" : false,
          "length" : 0,
          "precision" : 10,
          "generator" : "assigned",
          "isRelated" : true,
          "defaultValue" : "",
          "relatedColumnName" : "languageId",
          "targetTable" : "language",
          "scale" : 0
        }, {
          "fieldName" : "currency",
          "type" : "integer",
          "fullyQualifiedType" : "integer",
          "columnName" : "currency_id",
          "isPrimaryKey" : false,
          "notNull" : false,
          "length" : 0,
          "precision" : 10,
          "generator" : "assigned",
          "isRelated" : true,
          "defaultValue" : "",
          "relatedColumnName" : "currencyId",
          "targetTable" : "currency",
          "scale" : 0
        }, {
          "fieldName" : "id",
          "type" : "integer",
          "fullyQualifiedType" : "integer",
          "columnName" : "ID",
          "isPrimaryKey" : true,
          "notNull" : true,
          "length" : 0,
          "precision" : 10,
          "generator" : "identity",
          "isRelated" : false,
          "defaultValue" : "",
          "scale" : 0
        }, {
          "fieldName" : "currencyFormat",
          "type" : "string",
          "fullyQualifiedType" : "string",
          "columnName" : "currencyFormat",
          "isPrimaryKey" : false,
          "notNull" : false,
          "length" : 255,
          "precision" : 0,
          "generator" : "assigned",
          "isRelated" : false,
          "defaultValue" : "",
          "scale" : 0
        }, {
          "fieldName" : "dateFormat",
          "type" : "date",
          "fullyQualifiedType" : "date",
          "columnName" : "dateFormat",
          "isPrimaryKey" : false,
          "notNull" : false,
          "length" : 0,
          "precision" : 0,
          "generator" : "assigned",
          "isRelated" : false,
          "defaultValue" : "",
          "scale" : 0
        }, {
          "fieldName" : "name",
          "type" : "string",
          "fullyQualifiedType" : "string",
          "columnName" : "name",
          "isPrimaryKey" : false,
          "notNull" : false,
          "length" : 255,
          "precision" : 0,
          "generator" : "assigned",
          "isRelated" : false,
          "defaultValue" : "",
          "scale" : 0
        } ]
      }, {
        "fieldName" : "id",
        "type" : "integer",
        "fullyQualifiedType" : "integer",
        "columnName" : "ID",
        "isPrimaryKey" : true,
        "notNull" : true,
        "length" : 0,
        "precision" : 10,
        "generator" : "identity",
        "isRelated" : false,
        "scale" : 0
      }, {
        "fieldName" : "name",
        "type" : "string",
        "fullyQualifiedType" : "string",
        "columnName" : "name",
        "isPrimaryKey" : false,
        "notNull" : false,
        "length" : 100,
        "precision" : 0,
        "generator" : "assigned",
        "isRelated" : false,
        "scale" : 0
      }, {
        "fieldName" : "cod",
        "type" : "string",
        "fullyQualifiedType" : "string",
        "columnName" : "cod",
        "isPrimaryKey" : false,
        "notNull" : false,
        "length" : 255,
        "precision" : 0,
        "generator" : "assigned",
        "isRelated" : false,
        "defaultValue" : "",
        "scale" : 0
      }, {
        "fieldName" : "description",
        "type" : "string",
        "fullyQualifiedType" : "string",
        "columnName" : "description",
        "isPrimaryKey" : false,
        "notNull" : false,
        "length" : 255,
        "precision" : 0,
        "generator" : "assigned",
        "isRelated" : false,
        "scale" : 0
      }, {
        "fieldName" : "fiscalScope",
        "type" : "string",
        "fullyQualifiedType" : "string",
        "columnName" : "fiscalScope",
        "isPrimaryKey" : false,
        "notNull" : false,
        "length" : 255,
        "precision" : 0,
        "generator" : "assigned",
        "isRelated" : false,
        "defaultValue" : "",
        "scale" : 0
      }, {
        "fieldName" : "taxLevel",
        "type" : "string",
        "fullyQualifiedType" : "string",
        "columnName" : "taxLevel",
        "isPrimaryKey" : false,
        "notNull" : false,
        "length" : 255,
        "precision" : 0,
        "generator" : "assigned",
        "isRelated" : false,
        "defaultValue" : "",
        "scale" : 0
      }, {
        "fieldName" : "reasonForImmunity",
        "type" : "string",
        "fullyQualifiedType" : "string",
        "columnName" : "reasonForImmunity",
        "isPrimaryKey" : false,
        "notNull" : false,
        "length" : 255,
        "precision" : 0,
        "generator" : "assigned",
        "isRelated" : false,
        "defaultValue" : "",
        "scale" : 0
      }, {
        "fieldName" : "isCompound",
        "type" : "boolean",
        "fullyQualifiedType" : "boolean",
        "columnName" : "isCompound",
        "isPrimaryKey" : false,
        "notNull" : false,
        "length" : 0,
        "precision" : 1,
        "generator" : "assigned",
        "isRelated" : false,
        "defaultValue" : "",
        "scale" : 0
      }, {
        "fieldName" : "taxSale",
        "type" : "string",
        "fullyQualifiedType" : "string",
        "columnName" : "taxSale",
        "isPrimaryKey" : false,
        "notNull" : false,
        "length" : 255,
        "precision" : 0,
        "generator" : "assigned",
        "isRelated" : false,
        "defaultValue" : "",
        "scale" : 0
      }, {
        "fieldName" : "taxPurchase",
        "type" : "string",
        "fullyQualifiedType" : "string",
        "columnName" : "taxPurchase",
        "isPrimaryKey" : false,
        "notNull" : false,
        "length" : 255,
        "precision" : 0,
        "generator" : "assigned",
        "isRelated" : false,
        "defaultValue" : "",
        "scale" : 0
      } ],
      "entityName" : "Tax",
      "fullyQualifiedName" : "com.faturacaomodelo.dbinvoice.Tax",
      "tableType" : "TABLE",
      "primaryFields" : [ "id" ]
    },
    "isDefault" : true,
    "bindCount" : 2,
    "tableName" : "tax",
    "tableType" : "TABLE",
    "properties" : [ "taxType", "fiscalSpace", "country" ],
    "relatedTables" : [ {
      "columnName" : "taxType",
      "relationName" : "taxType",
      "type" : "TaxType",
      "watchOn" : "DbinvoiceTaxTypeData",
      "package" : "com.faturacaomodelo.dbinvoice.Tax"
    }, {
      "columnName" : "fiscalSpace",
      "relationName" : "fiscalSpace",
      "type" : "FiscalSpace",
      "watchOn" : "DbinvoiceFiscalSpaceData",
      "package" : "com.faturacaomodelo.dbinvoice.Tax"
    }, {
      "columnName" : "country",
      "relationName" : "country",
      "type" : "Country",
      "watchOn" : "DbinvoiceCountryData",
      "package" : "com.faturacaomodelo.dbinvoice.Tax"
    } ],
    "filterFields" : { },
    "inputFields" : { },
    "package" : "com.faturacaomodelo.dbinvoice.Tax"
  },
  "DbinvoiceTaxRateData" : {
    "_id" : "wm-DbinvoiceSaleTaxData-wm.LiveVariable-1499264599786",
    "name" : "DbinvoiceTaxRateData",
    "owner" : "Page",
    "category" : "wm.LiveVariable",
    "dataBinding" : [ ],
    "operation" : "read",
    "dataSet" : [ ],
    "type" : "TaxRate",
    "isList" : true,
    "saveInPhonegap" : false,
    "maxResults" : 20,
    "designMaxResults" : 10,
    "inFlightBehavior" : "executeLast",
    "startUpdate" : true,
    "autoUpdate" : true,
    "transformationRequired" : false,
    "liveSource" : "dbinvoice",
    "ignoreCase" : true,
    "matchMode" : "start",
    "propertiesMap" : {
      "columns" : [ {
        "fieldName" : "tax",
        "type" : "integer",
        "fullyQualifiedType" : "integer",
        "columnName" : "tax_id",
        "isPrimaryKey" : false,
        "notNull" : false,
        "length" : 0,
        "precision" : 10,
        "generator" : "assigned",
        "isRelated" : true,
        "relatedTableName" : "tax",
        "relatedEntityName" : "Tax",
        "relatedColumnName" : "taxId",
        "relatedFieldName" : "tax.id",
        "isList" : false,
        "targetTable" : "tax",
        "scale" : 0,
        "columns" : [ {
          "fieldName" : "taxType",
          "type" : "integer",
          "fullyQualifiedType" : "integer",
          "columnName" : "taxType_id",
          "isPrimaryKey" : false,
          "notNull" : false,
          "length" : 0,
          "precision" : 10,
          "generator" : "assigned",
          "isRelated" : true,
          "defaultValue" : "",
          "relatedColumnName" : "taxTypeId",
          "targetTable" : "taxType",
          "scale" : 0
        }, {
          "fieldName" : "fiscalSpace",
          "type" : "integer",
          "fullyQualifiedType" : "integer",
          "columnName" : "fiscalSpace_id",
          "isPrimaryKey" : false,
          "notNull" : false,
          "length" : 0,
          "precision" : 10,
          "generator" : "assigned",
          "isRelated" : true,
          "defaultValue" : "",
          "relatedColumnName" : "fiscalSpaceId",
          "targetTable" : "fiscalSpace",
          "scale" : 0
        }, {
          "fieldName" : "country",
          "type" : "integer",
          "fullyQualifiedType" : "integer",
          "columnName" : "country_id",
          "isPrimaryKey" : false,
          "notNull" : false,
          "length" : 0,
          "precision" : 10,
          "generator" : "assigned",
          "isRelated" : true,
          "defaultValue" : "",
          "relatedColumnName" : "countryId",
          "targetTable" : "country",
          "scale" : 0
        }, {
          "fieldName" : "id",
          "type" : "integer",
          "fullyQualifiedType" : "integer",
          "columnName" : "ID",
          "isPrimaryKey" : true,
          "notNull" : true,
          "length" : 0,
          "precision" : 10,
          "generator" : "identity",
          "isRelated" : false,
          "scale" : 0
        }, {
          "fieldName" : "name",
          "type" : "string",
          "fullyQualifiedType" : "string",
          "columnName" : "name",
          "isPrimaryKey" : false,
          "notNull" : false,
          "length" : 100,
          "precision" : 0,
          "generator" : "assigned",
          "isRelated" : false,
          "scale" : 0
        }, {
          "fieldName" : "cod",
          "type" : "string",
          "fullyQualifiedType" : "string",
          "columnName" : "cod",
          "isPrimaryKey" : false,
          "notNull" : false,
          "length" : 255,
          "precision" : 0,
          "generator" : "assigned",
          "isRelated" : false,
          "defaultValue" : "",
          "scale" : 0
        }, {
          "fieldName" : "description",
          "type" : "string",
          "fullyQualifiedType" : "string",
          "columnName" : "description",
          "isPrimaryKey" : false,
          "notNull" : false,
          "length" : 255,
          "precision" : 0,
          "generator" : "assigned",
          "isRelated" : false,
          "scale" : 0
        }, {
          "fieldName" : "fiscalScope",
          "type" : "string",
          "fullyQualifiedType" : "string",
          "columnName" : "fiscalScope",
          "isPrimaryKey" : false,
          "notNull" : false,
          "length" : 255,
          "precision" : 0,
          "generator" : "assigned",
          "isRelated" : false,
          "defaultValue" : "",
          "scale" : 0
        }, {
          "fieldName" : "taxLevel",
          "type" : "string",
          "fullyQualifiedType" : "string",
          "columnName" : "taxLevel",
          "isPrimaryKey" : false,
          "notNull" : false,
          "length" : 255,
          "precision" : 0,
          "generator" : "assigned",
          "isRelated" : false,
          "defaultValue" : "",
          "scale" : 0
        }, {
          "fieldName" : "reasonForImmunity",
          "type" : "string",
          "fullyQualifiedType" : "string",
          "columnName" : "reasonForImmunity",
          "isPrimaryKey" : false,
          "notNull" : false,
          "length" : 255,
          "precision" : 0,
          "generator" : "assigned",
          "isRelated" : false,
          "defaultValue" : "",
          "scale" : 0
        }, {
          "fieldName" : "isCompound",
          "type" : "boolean",
          "fullyQualifiedType" : "boolean",
          "columnName" : "isCompound",
          "isPrimaryKey" : false,
          "notNull" : false,
          "length" : 0,
          "precision" : 1,
          "generator" : "assigned",
          "isRelated" : false,
          "defaultValue" : "",
          "scale" : 0
        }, {
          "fieldName" : "taxSale",
          "type" : "string",
          "fullyQualifiedType" : "string",
          "columnName" : "taxSale",
          "isPrimaryKey" : false,
          "notNull" : false,
          "length" : 255,
          "precision" : 0,
          "generator" : "assigned",
          "isRelated" : false,
          "defaultValue" : "",
          "scale" : 0
        }, {
          "fieldName" : "taxPurchase",
          "type" : "string",
          "fullyQualifiedType" : "string",
          "columnName" : "taxPurchase",
          "isPrimaryKey" : false,
          "notNull" : false,
          "length" : 255,
          "precision" : 0,
          "generator" : "assigned",
          "isRelated" : false,
          "defaultValue" : "",
          "scale" : 0
        } ]
      }, {
        "fieldName" : "id",
        "type" : "integer",
        "fullyQualifiedType" : "integer",
        "columnName" : "ID",
        "isPrimaryKey" : true,
        "notNull" : true,
        "length" : 0,
        "precision" : 10,
        "generator" : "identity",
        "isRelated" : false,
        "scale" : 0
      }, {
        "fieldName" : "rate",
        "type" : "integer",
        "fullyQualifiedType" : "integer",
        "columnName" : "rate",
        "isPrimaryKey" : false,
        "notNull" : false,
        "length" : 0,
        "precision" : 10,
        "generator" : "assigned",
        "isRelated" : false,
        "defaultValue" : "",
        "scale" : 0
      }, {
        "fieldName" : "effectiveDate",
        "type" : "date",
        "fullyQualifiedType" : "date",
        "columnName" : "effectiveDate",
        "isPrimaryKey" : false,
        "notNull" : false,
        "length" : 0,
        "precision" : 0,
        "generator" : "assigned",
        "isRelated" : false,
        "defaultValue" : "",
        "scale" : 0
      } ],
      "entityName" : "TaxRate",
      "fullyQualifiedName" : "com.faturacaomodelo.dbinvoice.TaxRate",
      "tableType" : "TABLE",
      "primaryFields" : [ "id" ]
    },
    "isDefault" : true,
    "bindCount" : 3,
    "tableName" : "taxRate",
    "tableType" : "TABLE",
    "properties" : [ "tax" ],
    "relatedTables" : [ {
      "columnName" : "tax",
      "relationName" : "tax",
      "type" : "Tax",
      "watchOn" : "DbinvoiceTaxData",
      "package" : "com.faturacaomodelo.dbinvoice.TaxRate"
    } ],
    "filterFields" : { },
    "inputFields" : { },
    "package" : "com.faturacaomodelo.dbinvoice.TaxRate"
  },
  "DbinvoiceTaxTypeData" : {
    "_id" : "wm-DbinvoiceTaxTypeData-wm.LiveVariable-1500394248762",
    "name" : "DbinvoiceTaxTypeData",
    "owner" : "Page",
    "category" : "wm.LiveVariable",
    "dataBinding" : [ ],
    "operation" : "read",
    "dataSet" : [ ],
    "type" : "TaxType",
    "isList" : true,
    "saveInPhonegap" : false,
    "maxResults" : 20,
    "designMaxResults" : 10,
    "inFlightBehavior" : "executeLast",
    "startUpdate" : true,
    "autoUpdate" : true,
    "transformationRequired" : false,
    "liveSource" : "dbinvoice",
    "ignoreCase" : true,
    "matchMode" : "start",
    "orderBy" : "id asc",
    "propertiesMap" : {
      "columns" : [ {
        "fieldName" : "id",
        "type" : "integer",
        "fullyQualifiedType" : "integer",
        "columnName" : "ID",
        "isPrimaryKey" : true,
        "notNull" : true,
        "length" : 0,
        "precision" : 10,
        "generator" : "identity",
        "isRelated" : false,
        "defaultValue" : "",
        "scale" : 0
      }, {
        "fieldName" : "name",
        "type" : "string",
        "fullyQualifiedType" : "string",
        "columnName" : "name",
        "isPrimaryKey" : false,
        "notNull" : false,
        "length" : 255,
        "precision" : 0,
        "generator" : "assigned",
        "isRelated" : false,
        "defaultValue" : "",
        "scale" : 0
      } ],
      "entityName" : "TaxType",
      "fullyQualifiedName" : "com.faturacaomodelo.dbinvoice.TaxType",
      "tableType" : "TABLE",
      "primaryFields" : [ "id" ]
    },
    "isDefault" : true,
    "bindCount" : 1,
    "tableName" : "taxType",
    "tableType" : "TABLE",
    "properties" : [ ],
    "relatedTables" : [ ],
    "package" : "com.faturacaomodelo.dbinvoice.TaxType"
  }
}